[{"line":1,"elements":[{"line":3,"name":"","description":"","type":"background","keyword":"Background","steps":[{"name":"url \"http:\/\/localhost:8080\/engine-rest\"","result":{"duration":51600,"status":"passed"},"match":{"location":"karate","arguments":[]},"keyword":"Given","line":4,"doc_string":{"content_type":"","value":"00:01:36.858 karate.env system property was: demo \n","line":4}}]},{"line":32,"name":"Negociar Pedido com sucesso","description":"","id":"negociar-pedido-com-sucesso","type":"scenario","keyword":"Scenario Outline","steps":[{"name":"path \"\/process-definition\/key\/DaNegociacaoAEntregaDoPedidoProcess\/start\"","result":{"duration":87600,"status":"passed"},"match":{"location":"karate","arguments":[]},"keyword":"Given","line":7},{"name":"request","result":{"duration":216300,"status":"passed"},"match":{"location":"karate","arguments":[]},"keyword":"Given","line":8,"doc_string":{"content_type":"","value":"{\n    \"variables\": {\n        \"quantidadePedida\": {\"value\": 99, \"type\": \"Integer\"},\n        \"prazoPedido\": {\"value\": 0, \"type\": \"Integer\"},\n        \"nomeCliente\": {\"value\": Creusa, \"type\": \"String\"},\n        \"indicacao\": {\"value\": false, \"type\": \"Boolean\"},\n        \"comprou\": {\"value\": false, \"type\": \"Boolean\"},\n        \"pagou\": {\"value\": false, \"type\": \"Boolean\"}\n    },\n \"withVariablesInReturn\": true\n}","line":8}},{"name":"method POST","result":{"duration":435193800,"status":"passed"},"match":{"location":"karate","arguments":[]},"keyword":"When","line":22},{"name":"status 200","result":{"duration":8100,"status":"passed"},"match":{"location":"karate","arguments":[]},"keyword":"Then","line":23},{"name":"match $ == '#object'","result":{"duration":113000,"status":"passed"},"match":{"location":"karate","arguments":[]},"keyword":"And","line":24},{"name":"match $.variables.numeroPedido.value == '#present'","result":{"duration":152700,"status":"passed"},"match":{"location":"karate","arguments":[]},"keyword":"And","line":25},{"name":"match $.variables.valorPedido.value == 128.70","result":{"duration":479200,"status":"passed"},"match":{"location":"karate","arguments":[]},"keyword":"And","line":26},{"name":"match $.variables.pedidoValido.value == true","result":{"duration":158400,"status":"passed"},"match":{"location":"karate","arguments":[]},"keyword":"And","line":27},{"name":"match $.variables.msgValidacaoPedido.value == \"Pedido aceito\"","result":{"duration":409000,"status":"passed"},"match":{"location":"karate","arguments":[]},"keyword":"And","line":28}],"tags":[]},{"line":3,"name":"","description":"","type":"background","keyword":"Background","steps":[{"name":"url \"http:\/\/localhost:8080\/engine-rest\"","result":{"duration":46900,"status":"passed"},"match":{"location":"karate","arguments":[]},"keyword":"Given","line":4,"doc_string":{"content_type":"","value":"00:01:37.302 karate.env system property was: demo \n","line":4}}]},{"line":33,"name":"Negociar Pedido com sucesso","description":"","id":"negociar-pedido-com-sucesso","type":"scenario","keyword":"Scenario Outline","steps":[{"name":"path \"\/process-definition\/key\/DaNegociacaoAEntregaDoPedidoProcess\/start\"","result":{"duration":104200,"status":"passed"},"match":{"location":"karate","arguments":[]},"keyword":"Given","line":7},{"name":"request","result":{"duration":110400,"status":"passed"},"match":{"location":"karate","arguments":[]},"keyword":"Given","line":8,"doc_string":{"content_type":"","value":"{\n    \"variables\": {\n        \"quantidadePedida\": {\"value\": 100, \"type\": \"Integer\"},\n        \"prazoPedido\": {\"value\": 0, \"type\": \"Integer\"},\n        \"nomeCliente\": {\"value\": Creusa, \"type\": \"String\"},\n        \"indicacao\": {\"value\": true, \"type\": \"Boolean\"},\n        \"comprou\": {\"value\": true, \"type\": \"Boolean\"},\n        \"pagou\": {\"value\": true, \"type\": \"Boolean\"}\n    },\n \"withVariablesInReturn\": true\n}","line":8}},{"name":"method POST","result":{"duration":79218600,"status":"passed"},"match":{"location":"karate","arguments":[]},"keyword":"When","line":22},{"name":"status 200","result":{"duration":9700,"status":"passed"},"match":{"location":"karate","arguments":[]},"keyword":"Then","line":23},{"name":"match $ == '#object'","result":{"duration":260200,"status":"passed"},"match":{"location":"karate","arguments":[]},"keyword":"And","line":24},{"name":"match $.variables.numeroPedido.value == '#present'","result":{"duration":544000,"status":"passed"},"match":{"location":"karate","arguments":[]},"keyword":"And","line":25},{"name":"match $.variables.valorPedido.value == 130.00","result":{"duration":444300,"status":"passed"},"match":{"location":"karate","arguments":[]},"keyword":"And","line":26},{"name":"match $.variables.pedidoValido.value == true","result":{"duration":136500,"status":"passed"},"match":{"location":"karate","arguments":[]},"keyword":"And","line":27},{"name":"match $.variables.msgValidacaoPedido.value == \"Pedido aceito\"","result":{"duration":103700,"status":"passed"},"match":{"location":"karate","arguments":[]},"keyword":"And","line":28}],"tags":[]},{"line":3,"name":"","description":"","type":"background","keyword":"Background","steps":[{"name":"url \"http:\/\/localhost:8080\/engine-rest\"","result":{"duration":53500,"status":"passed"},"match":{"location":"karate","arguments":[]},"keyword":"Given","line":4,"doc_string":{"content_type":"","value":"00:01:37.386 karate.env system property was: demo \n","line":4}}]},{"line":34,"name":"Negociar Pedido com sucesso","description":"","id":"negociar-pedido-com-sucesso","type":"scenario","keyword":"Scenario Outline","steps":[{"name":"path \"\/process-definition\/key\/DaNegociacaoAEntregaDoPedidoProcess\/start\"","result":{"duration":79100,"status":"passed"},"match":{"location":"karate","arguments":[]},"keyword":"Given","line":7},{"name":"request","result":{"duration":109400,"status":"passed"},"match":{"location":"karate","arguments":[]},"keyword":"Given","line":8,"doc_string":{"content_type":"","value":"{\n    \"variables\": {\n        \"quantidadePedida\": {\"value\": 999, \"type\": \"Integer\"},\n        \"prazoPedido\": {\"value\": 0, \"type\": \"Integer\"},\n        \"nomeCliente\": {\"value\": Creusa, \"type\": \"String\"},\n        \"indicacao\": {\"value\": true, \"type\": \"Boolean\"},\n        \"comprou\": {\"value\": true, \"type\": \"Boolean\"},\n        \"pagou\": {\"value\": true, \"type\": \"Boolean\"}\n    },\n \"withVariablesInReturn\": true\n}","line":8}},{"name":"method POST","result":{"duration":80557600,"status":"passed"},"match":{"location":"karate","arguments":[]},"keyword":"When","line":22},{"name":"status 200","result":{"duration":8300,"status":"passed"},"match":{"location":"karate","arguments":[]},"keyword":"Then","line":23},{"name":"match $ == '#object'","result":{"duration":94100,"status":"passed"},"match":{"location":"karate","arguments":[]},"keyword":"And","line":24},{"name":"match $.variables.numeroPedido.value == '#present'","result":{"duration":109600,"status":"passed"},"match":{"location":"karate","arguments":[]},"keyword":"And","line":25},{"name":"match $.variables.valorPedido.value == 1298.70","result":{"duration":335100,"status":"passed"},"match":{"location":"karate","arguments":[]},"keyword":"And","line":26},{"name":"match $.variables.pedidoValido.value == true","result":{"duration":87300,"status":"passed"},"match":{"location":"karate","arguments":[]},"keyword":"And","line":27},{"name":"match $.variables.msgValidacaoPedido.value == \"Pedido aceito\"","result":{"duration":63100,"status":"passed"},"match":{"location":"karate","arguments":[]},"keyword":"And","line":28}],"tags":[]},{"line":3,"name":"","description":"","type":"background","keyword":"Background","steps":[{"name":"url \"http:\/\/localhost:8080\/engine-rest\"","result":{"duration":53400,"status":"passed"},"match":{"location":"karate","arguments":[]},"keyword":"Given","line":4,"doc_string":{"content_type":"","value":"00:01:37.471 karate.env system property was: demo \n","line":4}}]},{"line":35,"name":"Negociar Pedido com sucesso","description":"","id":"negociar-pedido-com-sucesso","type":"scenario","keyword":"Scenario Outline","steps":[{"name":"path \"\/process-definition\/key\/DaNegociacaoAEntregaDoPedidoProcess\/start\"","result":{"duration":89600,"status":"passed"},"match":{"location":"karate","arguments":[]},"keyword":"Given","line":7},{"name":"request","result":{"duration":140000,"status":"passed"},"match":{"location":"karate","arguments":[]},"keyword":"Given","line":8,"doc_string":{"content_type":"","value":"{\n    \"variables\": {\n        \"quantidadePedida\": {\"value\": 1001, \"type\": \"Integer\"},\n        \"prazoPedido\": {\"value\": 0, \"type\": \"Integer\"},\n        \"nomeCliente\": {\"value\": Creusa, \"type\": \"String\"},\n        \"indicacao\": {\"value\": true, \"type\": \"Boolean\"},\n        \"comprou\": {\"value\": true, \"type\": \"Boolean\"},\n        \"pagou\": {\"value\": true, \"type\": \"Boolean\"}\n    },\n \"withVariablesInReturn\": true\n}","line":8}},{"name":"method POST","result":{"duration":52831500,"status":"passed"},"match":{"location":"karate","arguments":[]},"keyword":"When","line":22},{"name":"status 200","result":{"duration":6800,"status":"passed"},"match":{"location":"karate","arguments":[]},"keyword":"Then","line":23},{"name":"match $ == '#object'","result":{"duration":89200,"status":"passed"},"match":{"location":"karate","arguments":[]},"keyword":"And","line":24},{"name":"match $.variables.numeroPedido.value == '#present'","result":{"duration":97300,"status":"passed"},"match":{"location":"karate","arguments":[]},"keyword":"And","line":25},{"name":"match $.variables.valorPedido.value == 1301.30","result":{"duration":322500,"status":"passed"},"match":{"location":"karate","arguments":[]},"keyword":"And","line":26},{"name":"match $.variables.pedidoValido.value == true","result":{"duration":94900,"status":"passed"},"match":{"location":"karate","arguments":[]},"keyword":"And","line":27},{"name":"match $.variables.msgValidacaoPedido.value == \"Pedido aceito\"","result":{"duration":64800,"status":"passed"},"match":{"location":"karate","arguments":[]},"keyword":"And","line":28}],"tags":[]},{"line":3,"name":"","description":"","type":"background","keyword":"Background","steps":[{"name":"url \"http:\/\/localhost:8080\/engine-rest\"","result":{"duration":54100,"status":"passed"},"match":{"location":"karate","arguments":[]},"keyword":"Given","line":4,"doc_string":{"content_type":"","value":"00:01:37.528 karate.env system property was: demo \n","line":4}}]},{"line":36,"name":"Negociar Pedido com sucesso","description":"","id":"negociar-pedido-com-sucesso","type":"scenario","keyword":"Scenario Outline","steps":[{"name":"path \"\/process-definition\/key\/DaNegociacaoAEntregaDoPedidoProcess\/start\"","result":{"duration":92900,"status":"passed"},"match":{"location":"karate","arguments":[]},"keyword":"Given","line":7},{"name":"request","result":{"duration":132200,"status":"passed"},"match":{"location":"karate","arguments":[]},"keyword":"Given","line":8,"doc_string":{"content_type":"","value":"{\n    \"variables\": {\n        \"quantidadePedida\": {\"value\": 99, \"type\": \"Integer\"},\n        \"prazoPedido\": {\"value\": 1, \"type\": \"Integer\"},\n        \"nomeCliente\": {\"value\": Creusa, \"type\": \"String\"},\n        \"indicacao\": {\"value\": false, \"type\": \"Boolean\"},\n        \"comprou\": {\"value\": false, \"type\": \"Boolean\"},\n        \"pagou\": {\"value\": false, \"type\": \"Boolean\"}\n    },\n \"withVariablesInReturn\": true\n}","line":8}},{"name":"method POST","result":{"duration":269350600,"status":"passed"},"match":{"location":"karate","arguments":[]},"keyword":"When","line":22},{"name":"status 200","result":{"duration":9200,"status":"passed"},"match":{"location":"karate","arguments":[]},"keyword":"Then","line":23},{"name":"match $ == '#object'","result":{"duration":139100,"status":"passed"},"match":{"location":"karate","arguments":[]},"keyword":"And","line":24},{"name":"match $.variables.numeroPedido.value == '#present'","result":{"duration":156000,"status":"passed"},"match":{"location":"karate","arguments":[]},"keyword":"And","line":25},{"name":"match $.variables.valorPedido.value == 128.70","result":{"duration":316100,"status":"passed"},"match":{"location":"karate","arguments":[]},"keyword":"And","line":26},{"name":"match $.variables.pedidoValido.value == true","result":{"duration":373300,"status":"passed"},"match":{"location":"karate","arguments":[]},"keyword":"And","line":27},{"name":"match $.variables.msgValidacaoPedido.value == \"Pedido aceito\"","result":{"duration":208900,"status":"passed"},"match":{"location":"karate","arguments":[]},"keyword":"And","line":28}],"tags":[]},{"line":3,"name":"","description":"","type":"background","keyword":"Background","steps":[{"name":"url \"http:\/\/localhost:8080\/engine-rest\"","result":{"duration":68000,"status":"passed"},"match":{"location":"karate","arguments":[]},"keyword":"Given","line":4,"doc_string":{"content_type":"","value":"00:01:37.805 karate.env system property was: demo \n","line":4}}]},{"line":37,"name":"Negociar Pedido com sucesso","description":"","id":"negociar-pedido-com-sucesso","type":"scenario","keyword":"Scenario Outline","steps":[{"name":"path \"\/process-definition\/key\/DaNegociacaoAEntregaDoPedidoProcess\/start\"","result":{"duration":114600,"status":"passed"},"match":{"location":"karate","arguments":[]},"keyword":"Given","line":7},{"name":"request","result":{"duration":171900,"status":"passed"},"match":{"location":"karate","arguments":[]},"keyword":"Given","line":8,"doc_string":{"content_type":"","value":"{\n    \"variables\": {\n        \"quantidadePedida\": {\"value\": 100, \"type\": \"Integer\"},\n        \"prazoPedido\": {\"value\": 1, \"type\": \"Integer\"},\n        \"nomeCliente\": {\"value\": Creusa, \"type\": \"String\"},\n        \"indicacao\": {\"value\": true, \"type\": \"Boolean\"},\n        \"comprou\": {\"value\": true, \"type\": \"Boolean\"},\n        \"pagou\": {\"value\": true, \"type\": \"Boolean\"}\n    },\n \"withVariablesInReturn\": true\n}","line":8}},{"name":"method POST","result":{"duration":69262300,"status":"passed"},"match":{"location":"karate","arguments":[]},"keyword":"When","line":22},{"name":"status 200","result":{"duration":9000,"status":"passed"},"match":{"location":"karate","arguments":[]},"keyword":"Then","line":23},{"name":"match $ == '#object'","result":{"duration":447000,"status":"passed"},"match":{"location":"karate","arguments":[]},"keyword":"And","line":24},{"name":"match $.variables.numeroPedido.value == '#present'","result":{"duration":185600,"status":"passed"},"match":{"location":"karate","arguments":[]},"keyword":"And","line":25},{"name":"match $.variables.valorPedido.value == 130.00","result":{"duration":162500,"status":"passed"},"match":{"location":"karate","arguments":[]},"keyword":"And","line":26},{"name":"match $.variables.pedidoValido.value == true","result":{"duration":138200,"status":"passed"},"match":{"location":"karate","arguments":[]},"keyword":"And","line":27},{"name":"match $.variables.msgValidacaoPedido.value == \"Pedido aceito\"","result":{"duration":124300,"status":"passed"},"match":{"location":"karate","arguments":[]},"keyword":"And","line":28}],"tags":[]},{"line":3,"name":"","description":"","type":"background","keyword":"Background","steps":[{"name":"url \"http:\/\/localhost:8080\/engine-rest\"","result":{"duration":68500,"status":"passed"},"match":{"location":"karate","arguments":[]},"keyword":"Given","line":4,"doc_string":{"content_type":"","value":"00:01:37.881 karate.env system property was: demo \n","line":4}}]},{"line":38,"name":"Negociar Pedido com sucesso","description":"","id":"negociar-pedido-com-sucesso","type":"scenario","keyword":"Scenario Outline","steps":[{"name":"path \"\/process-definition\/key\/DaNegociacaoAEntregaDoPedidoProcess\/start\"","result":{"duration":108900,"status":"passed"},"match":{"location":"karate","arguments":[]},"keyword":"Given","line":7},{"name":"request","result":{"duration":153400,"status":"passed"},"match":{"location":"karate","arguments":[]},"keyword":"Given","line":8,"doc_string":{"content_type":"","value":"{\n    \"variables\": {\n        \"quantidadePedida\": {\"value\": 999, \"type\": \"Integer\"},\n        \"prazoPedido\": {\"value\": 1, \"type\": \"Integer\"},\n        \"nomeCliente\": {\"value\": Creusa, \"type\": \"String\"},\n        \"indicacao\": {\"value\": true, \"type\": \"Boolean\"},\n        \"comprou\": {\"value\": true, \"type\": \"Boolean\"},\n        \"pagou\": {\"value\": true, \"type\": \"Boolean\"}\n    },\n \"withVariablesInReturn\": true\n}","line":8}},{"name":"method POST","result":{"duration":88889800,"status":"passed"},"match":{"location":"karate","arguments":[]},"keyword":"When","line":22},{"name":"status 200","result":{"duration":8200,"status":"passed"},"match":{"location":"karate","arguments":[]},"keyword":"Then","line":23},{"name":"match $ == '#object'","result":{"duration":94700,"status":"passed"},"match":{"location":"karate","arguments":[]},"keyword":"And","line":24},{"name":"match $.variables.numeroPedido.value == '#present'","result":{"duration":160300,"status":"passed"},"match":{"location":"karate","arguments":[]},"keyword":"And","line":25},{"name":"match $.variables.valorPedido.value == 1298.70","result":{"duration":159700,"status":"passed"},"match":{"location":"karate","arguments":[]},"keyword":"And","line":26},{"name":"match $.variables.pedidoValido.value == true","result":{"duration":121100,"status":"passed"},"match":{"location":"karate","arguments":[]},"keyword":"And","line":27},{"name":"match $.variables.msgValidacaoPedido.value == \"Pedido aceito\"","result":{"duration":98000,"status":"passed"},"match":{"location":"karate","arguments":[]},"keyword":"And","line":28}],"tags":[]},{"line":3,"name":"","description":"","type":"background","keyword":"Background","steps":[{"name":"url \"http:\/\/localhost:8080\/engine-rest\"","result":{"duration":50300,"status":"passed"},"match":{"location":"karate","arguments":[]},"keyword":"Given","line":4,"doc_string":{"content_type":"","value":"00:01:37.976 karate.env system property was: demo \n","line":4}}]},{"line":39,"name":"Negociar Pedido com sucesso","description":"","id":"negociar-pedido-com-sucesso","type":"scenario","keyword":"Scenario Outline","steps":[{"name":"path \"\/process-definition\/key\/DaNegociacaoAEntregaDoPedidoProcess\/start\"","result":{"duration":103700,"status":"passed"},"match":{"location":"karate","arguments":[]},"keyword":"Given","line":7},{"name":"request","result":{"duration":130800,"status":"passed"},"match":{"location":"karate","arguments":[]},"keyword":"Given","line":8,"doc_string":{"content_type":"","value":"{\n    \"variables\": {\n        \"quantidadePedida\": {\"value\": 1001, \"type\": \"Integer\"},\n        \"prazoPedido\": {\"value\": 1, \"type\": \"Integer\"},\n        \"nomeCliente\": {\"value\": Creusa, \"type\": \"String\"},\n        \"indicacao\": {\"value\": true, \"type\": \"Boolean\"},\n        \"comprou\": {\"value\": true, \"type\": \"Boolean\"},\n        \"pagou\": {\"value\": true, \"type\": \"Boolean\"}\n    },\n \"withVariablesInReturn\": true\n}","line":8}},{"name":"method POST","result":{"duration":86529100,"status":"passed"},"match":{"location":"karate","arguments":[]},"keyword":"When","line":22},{"name":"status 200","result":{"duration":8700,"status":"passed"},"match":{"location":"karate","arguments":[]},"keyword":"Then","line":23},{"name":"match $ == '#object'","result":{"duration":137600,"status":"passed"},"match":{"location":"karate","arguments":[]},"keyword":"And","line":24},{"name":"match $.variables.numeroPedido.value == '#present'","result":{"duration":163700,"status":"passed"},"match":{"location":"karate","arguments":[]},"keyword":"And","line":25},{"name":"match $.variables.valorPedido.value == 1301.30","result":{"duration":115700,"status":"passed"},"match":{"location":"karate","arguments":[]},"keyword":"And","line":26},{"name":"match $.variables.pedidoValido.value == true","result":{"duration":94100,"status":"passed"},"match":{"location":"karate","arguments":[]},"keyword":"And","line":27},{"name":"match $.variables.msgValidacaoPedido.value == \"Pedido aceito\"","result":{"duration":81100,"status":"passed"},"match":{"location":"karate","arguments":[]},"keyword":"And","line":28}],"tags":[]},{"line":3,"name":"","description":"","type":"background","keyword":"Background","steps":[{"name":"url \"http:\/\/localhost:8080\/engine-rest\"","result":{"duration":48900,"status":"passed"},"match":{"location":"karate","arguments":[]},"keyword":"Given","line":4,"doc_string":{"content_type":"","value":"00:01:38.071 karate.env system property was: demo \n","line":4}}]},{"line":40,"name":"Negociar Pedido com sucesso","description":"","id":"negociar-pedido-com-sucesso","type":"scenario","keyword":"Scenario Outline","steps":[{"name":"path \"\/process-definition\/key\/DaNegociacaoAEntregaDoPedidoProcess\/start\"","result":{"duration":80200,"status":"passed"},"match":{"location":"karate","arguments":[]},"keyword":"Given","line":7},{"name":"request","result":{"duration":152000,"status":"passed"},"match":{"location":"karate","arguments":[]},"keyword":"Given","line":8,"doc_string":{"content_type":"","value":"{\n    \"variables\": {\n        \"quantidadePedida\": {\"value\": 100, \"type\": \"Integer\"},\n        \"prazoPedido\": {\"value\": 1, \"type\": \"Integer\"},\n        \"nomeCliente\": {\"value\": Maria, \"type\": \"String\"},\n        \"indicacao\": {\"value\": false, \"type\": \"Boolean\"},\n        \"comprou\": {\"value\": true, \"type\": \"Boolean\"},\n        \"pagou\": {\"value\": true, \"type\": \"Boolean\"}\n    },\n \"withVariablesInReturn\": true\n}","line":8}},{"name":"method POST","result":{"duration":123304400,"status":"passed"},"match":{"location":"karate","arguments":[]},"keyword":"When","line":22},{"name":"status 200","result":{"duration":7900,"status":"passed"},"match":{"location":"karate","arguments":[]},"keyword":"Then","line":23},{"name":"match $ == '#object'","result":{"duration":148900,"status":"passed"},"match":{"location":"karate","arguments":[]},"keyword":"And","line":24},{"name":"match $.variables.numeroPedido.value == '#present'","result":{"duration":157400,"status":"passed"},"match":{"location":"karate","arguments":[]},"keyword":"And","line":25},{"name":"match $.variables.valorPedido.value == 160.00","result":{"duration":513700,"status":"passed"},"match":{"location":"karate","arguments":[]},"keyword":"And","line":26},{"name":"match $.variables.pedidoValido.value == true","result":{"duration":155500,"status":"passed"},"match":{"location":"karate","arguments":[]},"keyword":"And","line":27},{"name":"match $.variables.msgValidacaoPedido.value == \"Pedido aceito\"","result":{"duration":128700,"status":"passed"},"match":{"location":"karate","arguments":[]},"keyword":"And","line":28}],"tags":[]},{"line":3,"name":"","description":"","type":"background","keyword":"Background","steps":[{"name":"url \"http:\/\/localhost:8080\/engine-rest\"","result":{"duration":61800,"status":"passed"},"match":{"location":"karate","arguments":[]},"keyword":"Given","line":4,"doc_string":{"content_type":"","value":"00:01:38.201 karate.env system property was: demo \n","line":4}}]},{"line":41,"name":"Negociar Pedido com sucesso","description":"","id":"negociar-pedido-com-sucesso","type":"scenario","keyword":"Scenario Outline","steps":[{"name":"path \"\/process-definition\/key\/DaNegociacaoAEntregaDoPedidoProcess\/start\"","result":{"duration":101200,"status":"passed"},"match":{"location":"karate","arguments":[]},"keyword":"Given","line":7},{"name":"request","result":{"duration":152800,"status":"passed"},"match":{"location":"karate","arguments":[]},"keyword":"Given","line":8,"doc_string":{"content_type":"","value":"{\n    \"variables\": {\n        \"quantidadePedida\": {\"value\": 100, \"type\": \"Integer\"},\n        \"prazoPedido\": {\"value\": 1, \"type\": \"Integer\"},\n        \"nomeCliente\": {\"value\": Maria, \"type\": \"String\"},\n        \"indicacao\": {\"value\": true, \"type\": \"Boolean\"},\n        \"comprou\": {\"value\": false, \"type\": \"Boolean\"},\n        \"pagou\": {\"value\": false, \"type\": \"Boolean\"}\n    },\n \"withVariablesInReturn\": true\n}","line":8}},{"name":"method POST","result":{"duration":122677700,"status":"passed"},"match":{"location":"karate","arguments":[]},"keyword":"When","line":22},{"name":"status 200","result":{"duration":8100,"status":"passed"},"match":{"location":"karate","arguments":[]},"keyword":"Then","line":23},{"name":"match $ == '#object'","result":{"duration":152300,"status":"passed"},"match":{"location":"karate","arguments":[]},"keyword":"And","line":24},{"name":"match $.variables.numeroPedido.value == '#present'","result":{"duration":141000,"status":"passed"},"match":{"location":"karate","arguments":[]},"keyword":"And","line":25},{"name":"match $.variables.valorPedido.value == 160.00","result":{"duration":165900,"status":"passed"},"match":{"location":"karate","arguments":[]},"keyword":"And","line":26},{"name":"match $.variables.pedidoValido.value == true","result":{"duration":121100,"status":"passed"},"match":{"location":"karate","arguments":[]},"keyword":"And","line":27},{"name":"match $.variables.msgValidacaoPedido.value == \"Pedido aceito\"","result":{"duration":112600,"status":"passed"},"match":{"location":"karate","arguments":[]},"keyword":"And","line":28}],"tags":[]},{"line":3,"name":"","description":"","type":"background","keyword":"Background","steps":[{"name":"url \"http:\/\/localhost:8080\/engine-rest\"","result":{"duration":47100,"status":"passed"},"match":{"location":"karate","arguments":[]},"keyword":"Given","line":4,"doc_string":{"content_type":"","value":"00:01:38.329 karate.env system property was: demo \n","line":4}}]},{"line":42,"name":"Negociar Pedido com sucesso","description":"","id":"negociar-pedido-com-sucesso","type":"scenario","keyword":"Scenario Outline","steps":[{"name":"path \"\/process-definition\/key\/DaNegociacaoAEntregaDoPedidoProcess\/start\"","result":{"duration":156400,"status":"passed"},"match":{"location":"karate","arguments":[]},"keyword":"Given","line":7},{"name":"request","result":{"duration":130800,"status":"passed"},"match":{"location":"karate","arguments":[]},"keyword":"Given","line":8,"doc_string":{"content_type":"","value":"{\n    \"variables\": {\n        \"quantidadePedida\": {\"value\": 999, \"type\": \"Integer\"},\n        \"prazoPedido\": {\"value\": 1, \"type\": \"Integer\"},\n        \"nomeCliente\": {\"value\": Maria, \"type\": \"String\"},\n        \"indicacao\": {\"value\": false, \"type\": \"Boolean\"},\n        \"comprou\": {\"value\": true, \"type\": \"Boolean\"},\n        \"pagou\": {\"value\": true, \"type\": \"Boolean\"}\n    },\n \"withVariablesInReturn\": true\n}","line":8}},{"name":"method POST","result":{"duration":84454000,"status":"passed"},"match":{"location":"karate","arguments":[]},"keyword":"When","line":22},{"name":"status 200","result":{"duration":8000,"status":"passed"},"match":{"location":"karate","arguments":[]},"keyword":"Then","line":23},{"name":"match $ == '#object'","result":{"duration":102000,"status":"passed"},"match":{"location":"karate","arguments":[]},"keyword":"And","line":24},{"name":"match $.variables.numeroPedido.value == '#present'","result":{"duration":123200,"status":"passed"},"match":{"location":"karate","arguments":[]},"keyword":"And","line":25},{"name":"match $.variables.valorPedido.value == 1598.40","result":{"duration":641600,"status":"passed"},"match":{"location":"karate","arguments":[]},"keyword":"And","line":26},{"name":"match $.variables.pedidoValido.value == true","result":{"duration":221500,"status":"passed"},"match":{"location":"karate","arguments":[]},"keyword":"And","line":27},{"name":"match $.variables.msgValidacaoPedido.value == \"Pedido aceito\"","result":{"duration":150100,"status":"passed"},"match":{"location":"karate","arguments":[]},"keyword":"And","line":28}],"tags":[]},{"line":3,"name":"","description":"","type":"background","keyword":"Background","steps":[{"name":"url \"http:\/\/localhost:8080\/engine-rest\"","result":{"duration":47200,"status":"passed"},"match":{"location":"karate","arguments":[]},"keyword":"Given","line":4,"doc_string":{"content_type":"","value":"00:01:38.419 karate.env system property was: demo \n","line":4}}]},{"line":43,"name":"Negociar Pedido com sucesso","description":"","id":"negociar-pedido-com-sucesso","type":"scenario","keyword":"Scenario Outline","steps":[{"name":"path \"\/process-definition\/key\/DaNegociacaoAEntregaDoPedidoProcess\/start\"","result":{"duration":85200,"status":"passed"},"match":{"location":"karate","arguments":[]},"keyword":"Given","line":7},{"name":"request","result":{"duration":118300,"status":"passed"},"match":{"location":"karate","arguments":[]},"keyword":"Given","line":8,"doc_string":{"content_type":"","value":"{\n    \"variables\": {\n        \"quantidadePedida\": {\"value\": 999, \"type\": \"Integer\"},\n        \"prazoPedido\": {\"value\": 1, \"type\": \"Integer\"},\n        \"nomeCliente\": {\"value\": Maria, \"type\": \"String\"},\n        \"indicacao\": {\"value\": true, \"type\": \"Boolean\"},\n        \"comprou\": {\"value\": false, \"type\": \"Boolean\"},\n        \"pagou\": {\"value\": false, \"type\": \"Boolean\"}\n    },\n \"withVariablesInReturn\": true\n}","line":8}},{"name":"method POST","result":{"duration":88454500,"status":"passed"},"match":{"location":"karate","arguments":[]},"keyword":"When","line":22},{"name":"status 200","result":{"duration":8800,"status":"passed"},"match":{"location":"karate","arguments":[]},"keyword":"Then","line":23},{"name":"match $ == '#object'","result":{"duration":127800,"status":"passed"},"match":{"location":"karate","arguments":[]},"keyword":"And","line":24},{"name":"match $.variables.numeroPedido.value == '#present'","result":{"duration":223300,"status":"passed"},"match":{"location":"karate","arguments":[]},"keyword":"And","line":25},{"name":"match $.variables.valorPedido.value == 1598.40","result":{"duration":134600,"status":"passed"},"match":{"location":"karate","arguments":[]},"keyword":"And","line":26},{"name":"match $.variables.pedidoValido.value == true","result":{"duration":111600,"status":"passed"},"match":{"location":"karate","arguments":[]},"keyword":"And","line":27},{"name":"match $.variables.msgValidacaoPedido.value == \"Pedido aceito\"","result":{"duration":97000,"status":"passed"},"match":{"location":"karate","arguments":[]},"keyword":"And","line":28}],"tags":[]},{"line":3,"name":"","description":"","type":"background","keyword":"Background","steps":[{"name":"url \"http:\/\/localhost:8080\/engine-rest\"","result":{"duration":47700,"status":"passed"},"match":{"location":"karate","arguments":[]},"keyword":"Given","line":4,"doc_string":{"content_type":"","value":"00:01:38.513 karate.env system property was: demo \n","line":4}}]},{"line":47,"name":"Negociar Pedido com sucesso","description":"","id":"negociar-pedido-com-sucesso","type":"scenario","keyword":"Scenario Outline","steps":[{"name":"path \"\/process-definition\/key\/DaNegociacaoAEntregaDoPedidoProcess\/start\"","result":{"duration":89600,"status":"passed"},"match":{"location":"karate","arguments":[]},"keyword":"Given","line":7},{"name":"request","result":{"duration":145200,"status":"passed"},"match":{"location":"karate","arguments":[]},"keyword":"Given","line":8,"doc_string":{"content_type":"","value":"{\n    \"variables\": {\n        \"quantidadePedida\": {\"value\": 100, \"type\": \"Integer\"},\n        \"prazoPedido\": {\"value\": 0, \"type\": \"Integer\"},\n        \"nomeCliente\": {\"value\": Maria, \"type\": \"String\"},\n        \"indicacao\": {\"value\": true, \"type\": \"Boolean\"},\n        \"comprou\": {\"value\": true, \"type\": \"Boolean\"},\n        \"pagou\": {\"value\": true, \"type\": \"Boolean\"}\n    },\n \"withVariablesInReturn\": true\n}","line":8}},{"name":"method POST","result":{"duration":106088300,"status":"passed"},"match":{"location":"karate","arguments":[]},"keyword":"When","line":22},{"name":"status 200","result":{"duration":7900,"status":"passed"},"match":{"location":"karate","arguments":[]},"keyword":"Then","line":23},{"name":"match $ == '#object'","result":{"duration":105200,"status":"passed"},"match":{"location":"karate","arguments":[]},"keyword":"And","line":24},{"name":"match $.variables.numeroPedido.value == '#present'","result":{"duration":140300,"status":"passed"},"match":{"location":"karate","arguments":[]},"keyword":"And","line":25},{"name":"match $.variables.valorPedido.value == '#notpresent'","result":{"duration":1286900,"status":"passed"},"match":{"location":"karate","arguments":[]},"keyword":"And","line":26},{"name":"match $.variables.pedidoValido.value == false","result":{"duration":544600,"status":"passed"},"match":{"location":"karate","arguments":[]},"keyword":"And","line":27},{"name":"match $.variables.msgValidacaoPedido.value == \"Pedido n達o vale a pena\"","result":{"duration":366500,"status":"passed"},"match":{"location":"karate","arguments":[]},"keyword":"And","line":28}],"tags":[]},{"line":3,"name":"","description":"","type":"background","keyword":"Background","steps":[{"name":"url \"http:\/\/localhost:8080\/engine-rest\"","result":{"duration":48800,"status":"passed"},"match":{"location":"karate","arguments":[]},"keyword":"Given","line":4,"doc_string":{"content_type":"","value":"00:01:38.626 karate.env system property was: demo \n","line":4}}]},{"line":48,"name":"Negociar Pedido com sucesso","description":"","id":"negociar-pedido-com-sucesso","type":"scenario","keyword":"Scenario Outline","steps":[{"name":"path \"\/process-definition\/key\/DaNegociacaoAEntregaDoPedidoProcess\/start\"","result":{"duration":81400,"status":"passed"},"match":{"location":"karate","arguments":[]},"keyword":"Given","line":7},{"name":"request","result":{"duration":140400,"status":"passed"},"match":{"location":"karate","arguments":[]},"keyword":"Given","line":8,"doc_string":{"content_type":"","value":"{\n    \"variables\": {\n        \"quantidadePedida\": {\"value\": 999, \"type\": \"Integer\"},\n        \"prazoPedido\": {\"value\": 0, \"type\": \"Integer\"},\n        \"nomeCliente\": {\"value\": Maria, \"type\": \"String\"},\n        \"indicacao\": {\"value\": true, \"type\": \"Boolean\"},\n        \"comprou\": {\"value\": true, \"type\": \"Boolean\"},\n        \"pagou\": {\"value\": true, \"type\": \"Boolean\"}\n    },\n \"withVariablesInReturn\": true\n}","line":8}},{"name":"method POST","result":{"duration":221179400,"status":"passed"},"match":{"location":"karate","arguments":[]},"keyword":"When","line":22},{"name":"status 200","result":{"duration":8000,"status":"passed"},"match":{"location":"karate","arguments":[]},"keyword":"Then","line":23},{"name":"match $ == '#object'","result":{"duration":101000,"status":"passed"},"match":{"location":"karate","arguments":[]},"keyword":"And","line":24},{"name":"match $.variables.numeroPedido.value == '#present'","result":{"duration":174000,"status":"passed"},"match":{"location":"karate","arguments":[]},"keyword":"And","line":25},{"name":"match $.variables.valorPedido.value == '#notpresent'","result":{"duration":146600,"status":"passed"},"match":{"location":"karate","arguments":[]},"keyword":"And","line":26},{"name":"match $.variables.pedidoValido.value == false","result":{"duration":94800,"status":"passed"},"match":{"location":"karate","arguments":[]},"keyword":"And","line":27},{"name":"match $.variables.msgValidacaoPedido.value == \"Pedido n達o vale a pena\"","result":{"duration":82600,"status":"passed"},"match":{"location":"karate","arguments":[]},"keyword":"And","line":28}],"tags":[]},{"line":3,"name":"","description":"","type":"background","keyword":"Background","steps":[{"name":"url \"http:\/\/localhost:8080\/engine-rest\"","result":{"duration":40700,"status":"passed"},"match":{"location":"karate","arguments":[]},"keyword":"Given","line":4,"doc_string":{"content_type":"","value":"00:01:38.852 karate.env system property was: demo \n","line":4}}]},{"line":49,"name":"Negociar Pedido com sucesso","description":"","id":"negociar-pedido-com-sucesso","type":"scenario","keyword":"Scenario Outline","steps":[{"name":"path \"\/process-definition\/key\/DaNegociacaoAEntregaDoPedidoProcess\/start\"","result":{"duration":62700,"status":"passed"},"match":{"location":"karate","arguments":[]},"keyword":"Given","line":7},{"name":"request","result":{"duration":114000,"status":"passed"},"match":{"location":"karate","arguments":[]},"keyword":"Given","line":8,"doc_string":{"content_type":"","value":"{\n    \"variables\": {\n        \"quantidadePedida\": {\"value\": 99, \"type\": \"Integer\"},\n        \"prazoPedido\": {\"value\": 1, \"type\": \"Integer\"},\n        \"nomeCliente\": {\"value\": Maria, \"type\": \"String\"},\n        \"indicacao\": {\"value\": true, \"type\": \"Boolean\"},\n        \"comprou\": {\"value\": true, \"type\": \"Boolean\"},\n        \"pagou\": {\"value\": true, \"type\": \"Boolean\"}\n    },\n \"withVariablesInReturn\": true\n}","line":8}},{"name":"method POST","result":{"duration":190151200,"status":"passed"},"match":{"location":"karate","arguments":[]},"keyword":"When","line":22},{"name":"status 200","result":{"duration":8500,"status":"passed"},"match":{"location":"karate","arguments":[]},"keyword":"Then","line":23},{"name":"match $ == '#object'","result":{"duration":113000,"status":"passed"},"match":{"location":"karate","arguments":[]},"keyword":"And","line":24},{"name":"match $.variables.numeroPedido.value == '#present'","result":{"duration":138600,"status":"passed"},"match":{"location":"karate","arguments":[]},"keyword":"And","line":25},{"name":"match $.variables.valorPedido.value == '#notpresent'","result":{"duration":155700,"status":"passed"},"match":{"location":"karate","arguments":[]},"keyword":"And","line":26},{"name":"match $.variables.pedidoValido.value == false","result":{"duration":115700,"status":"passed"},"match":{"location":"karate","arguments":[]},"keyword":"And","line":27},{"name":"match $.variables.msgValidacaoPedido.value == \"Pedido n達o vale a pena\"","result":{"duration":94500,"status":"passed"},"match":{"location":"karate","arguments":[]},"keyword":"And","line":28}],"tags":[]},{"line":3,"name":"","description":"","type":"background","keyword":"Background","steps":[{"name":"url \"http:\/\/localhost:8080\/engine-rest\"","result":{"duration":46200,"status":"passed"},"match":{"location":"karate","arguments":[]},"keyword":"Given","line":4,"doc_string":{"content_type":"","value":"00:01:39.047 karate.env system property was: demo \n","line":4}}]},{"line":50,"name":"Negociar Pedido com sucesso","description":"","id":"negociar-pedido-com-sucesso","type":"scenario","keyword":"Scenario Outline","steps":[{"name":"path \"\/process-definition\/key\/DaNegociacaoAEntregaDoPedidoProcess\/start\"","result":{"duration":72200,"status":"passed"},"match":{"location":"karate","arguments":[]},"keyword":"Given","line":7},{"name":"request","result":{"duration":1030100,"status":"passed"},"match":{"location":"karate","arguments":[]},"keyword":"Given","line":8,"doc_string":{"content_type":"","value":"{\n    \"variables\": {\n        \"quantidadePedida\": {\"value\": 1001, \"type\": \"Integer\"},\n        \"prazoPedido\": {\"value\": 1, \"type\": \"Integer\"},\n        \"nomeCliente\": {\"value\": Maria, \"type\": \"String\"},\n        \"indicacao\": {\"value\": true, \"type\": \"Boolean\"},\n        \"comprou\": {\"value\": true, \"type\": \"Boolean\"},\n        \"pagou\": {\"value\": true, \"type\": \"Boolean\"}\n    },\n \"withVariablesInReturn\": true\n}","line":8}},{"name":"method POST","result":{"duration":103561700,"status":"passed"},"match":{"location":"karate","arguments":[]},"keyword":"When","line":22},{"name":"status 200","result":{"duration":7300,"status":"passed"},"match":{"location":"karate","arguments":[]},"keyword":"Then","line":23},{"name":"match $ == '#object'","result":{"duration":171000,"status":"passed"},"match":{"location":"karate","arguments":[]},"keyword":"And","line":24},{"name":"match $.variables.numeroPedido.value == '#present'","result":{"duration":296600,"status":"passed"},"match":{"location":"karate","arguments":[]},"keyword":"And","line":25},{"name":"match $.variables.valorPedido.value == '#notpresent'","result":{"duration":293900,"status":"passed"},"match":{"location":"karate","arguments":[]},"keyword":"And","line":26},{"name":"match $.variables.pedidoValido.value == false","result":{"duration":186500,"status":"passed"},"match":{"location":"karate","arguments":[]},"keyword":"And","line":27},{"name":"match $.variables.msgValidacaoPedido.value == \"Pedido n達o vale a pena\"","result":{"duration":112000,"status":"passed"},"match":{"location":"karate","arguments":[]},"keyword":"And","line":28}],"tags":[]},{"line":3,"name":"","description":"","type":"background","keyword":"Background","steps":[{"name":"url \"http:\/\/localhost:8080\/engine-rest\"","result":{"duration":45800,"status":"passed"},"match":{"location":"karate","arguments":[]},"keyword":"Given","line":4,"doc_string":{"content_type":"","value":"00:01:39.156 karate.env system property was: demo \n","line":4}}]},{"line":51,"name":"Negociar Pedido com sucesso","description":"","id":"negociar-pedido-com-sucesso","type":"scenario","keyword":"Scenario Outline","steps":[{"name":"path \"\/process-definition\/key\/DaNegociacaoAEntregaDoPedidoProcess\/start\"","result":{"duration":77300,"status":"passed"},"match":{"location":"karate","arguments":[]},"keyword":"Given","line":7},{"name":"request","result":{"duration":140300,"status":"passed"},"match":{"location":"karate","arguments":[]},"keyword":"Given","line":8,"doc_string":{"content_type":"","value":"{\n    \"variables\": {\n        \"quantidadePedida\": {\"value\": 100, \"type\": \"Integer\"},\n        \"prazoPedido\": {\"value\": 1, \"type\": \"Integer\"},\n        \"nomeCliente\": {\"value\": Maria, \"type\": \"String\"},\n        \"indicacao\": {\"value\": true, \"type\": \"Boolean\"},\n        \"comprou\": {\"value\": true, \"type\": \"Boolean\"},\n        \"pagou\": {\"value\": false, \"type\": \"Boolean\"}\n    },\n \"withVariablesInReturn\": true\n}","line":8}},{"name":"method POST","result":{"duration":118968800,"status":"passed"},"match":{"location":"karate","arguments":[]},"keyword":"When","line":22},{"name":"status 200","result":{"duration":8300,"status":"passed"},"match":{"location":"karate","arguments":[]},"keyword":"Then","line":23},{"name":"match $ == '#object'","result":{"duration":109800,"status":"passed"},"match":{"location":"karate","arguments":[]},"keyword":"And","line":24},{"name":"match $.variables.numeroPedido.value == '#present'","result":{"duration":152200,"status":"passed"},"match":{"location":"karate","arguments":[]},"keyword":"And","line":25},{"name":"match $.variables.valorPedido.value == '#notpresent'","result":{"duration":172700,"status":"passed"},"match":{"location":"karate","arguments":[]},"keyword":"And","line":26},{"name":"match $.variables.pedidoValido.value == false","result":{"duration":138000,"status":"passed"},"match":{"location":"karate","arguments":[]},"keyword":"And","line":27},{"name":"match $.variables.msgValidacaoPedido.value == \"Pedido de cliente ruim\"","result":{"duration":487000,"status":"passed"},"match":{"location":"karate","arguments":[]},"keyword":"And","line":28}],"tags":[]},{"line":3,"name":"","description":"","type":"background","keyword":"Background","steps":[{"name":"url \"http:\/\/localhost:8080\/engine-rest\"","result":{"duration":90800,"status":"passed"},"match":{"location":"karate","arguments":[]},"keyword":"Given","line":4,"doc_string":{"content_type":"","value":"00:01:39.282 karate.env system property was: demo \n","line":4}}]},{"line":52,"name":"Negociar Pedido com sucesso","description":"","id":"negociar-pedido-com-sucesso","type":"scenario","keyword":"Scenario Outline","steps":[{"name":"path \"\/process-definition\/key\/DaNegociacaoAEntregaDoPedidoProcess\/start\"","result":{"duration":123400,"status":"passed"},"match":{"location":"karate","arguments":[]},"keyword":"Given","line":7},{"name":"request","result":{"duration":133000,"status":"passed"},"match":{"location":"karate","arguments":[]},"keyword":"Given","line":8,"doc_string":{"content_type":"","value":"{\n    \"variables\": {\n        \"quantidadePedida\": {\"value\": 100, \"type\": \"Integer\"},\n        \"prazoPedido\": {\"value\": 1, \"type\": \"Integer\"},\n        \"nomeCliente\": {\"value\": Maria, \"type\": \"String\"},\n        \"indicacao\": {\"value\": false, \"type\": \"Boolean\"},\n        \"comprou\": {\"value\": false, \"type\": \"Boolean\"},\n        \"pagou\": {\"value\": false, \"type\": \"Boolean\"}\n    },\n \"withVariablesInReturn\": true\n}","line":8}},{"name":"method POST","result":{"duration":73725800,"status":"passed"},"match":{"location":"karate","arguments":[]},"keyword":"When","line":22},{"name":"status 200","result":{"duration":6900,"status":"passed"},"match":{"location":"karate","arguments":[]},"keyword":"Then","line":23},{"name":"match $ == '#object'","result":{"duration":80800,"status":"passed"},"match":{"location":"karate","arguments":[]},"keyword":"And","line":24},{"name":"match $.variables.numeroPedido.value == '#present'","result":{"duration":99700,"status":"passed"},"match":{"location":"karate","arguments":[]},"keyword":"And","line":25},{"name":"match $.variables.valorPedido.value == '#notpresent'","result":{"duration":160300,"status":"passed"},"match":{"location":"karate","arguments":[]},"keyword":"And","line":26},{"name":"match $.variables.pedidoValido.value == false","result":{"duration":103900,"status":"passed"},"match":{"location":"karate","arguments":[]},"keyword":"And","line":27},{"name":"match $.variables.msgValidacaoPedido.value == \"Pedido de cliente ruim\"","result":{"duration":131500,"status":"passed"},"match":{"location":"karate","arguments":[]},"keyword":"And","line":28}],"tags":[]}],"name":"brigadeiros\/features\/NegociarPedido.feature","description":"Negociar Pedido","id":"negociar-pedido","keyword":"Feature","uri":"brigadeiros\/features\/NegociarPedido.feature"}]